class_cli/__init__.py
class_cli/_cli.py
class_cli/_cli_exception.py
class_cli/_cli_logger.py
class_cli/_cli_methods.py
class_cli/_cli_parser.py
class_cli/_cli_prompt.py
class_cli/_cli_session.py
class_cli/_colors.py
class_cli-0.3.3.dist-info/LICENSE
class_cli-0.3.3.dist-info/METADATA
class_cli-0.3.3.dist-info/WHEEL
class_cli-0.3.3.dist-info/top_level.txt
class_cli-0.3.3.dist-info/RECORD
