Metadata-Version: 2.1
Name: class-cli
Version: 0.3.3
Summary: Converts a python class into a CLI program
Home-page: https://github.com/yoavhayun/CLI
Author: Yoav Hayun
Author-email: yoavhayun@gmail.com
License: GNU General Public License v3.0
Platform: UNKNOWN
Requires-Python: >=3.0
Requires-Dist: prompt-toolkit (>=3.0)
